lafhterlearn/__init__.py
lafhterlearn/augmentation.py
lafhterlearn/config_utils.py
lafhterlearn/configuration.py
lafhterlearn/data_generator.py
lafhterlearn/datasets.py
lafhterlearn/decoding.py
lafhterlearn/environment.py
lafhterlearn/evaluation.py
lafhterlearn/formatters.py
lafhterlearn/history_saver.py
lafhterlearn/image_pipelines.py
lafhterlearn/image_utils.py
lafhterlearn/loss_functions.py
lafhterlearn/metrics.py
lafhterlearn/models.py
lafhterlearn/ngram_utils.py
lafhterlearn/ngrams.py
lafhterlearn/recognition.py
lafhterlearn/session.py
lafhterlearn/tokenizer.py
lafhterlearn/training.py
lafhterlearn/utils.py
lafhterlearn/word_samplers.py
lafhterlearn/cmd_api/__init__.py
lafhterlearn/cmd_api/base.py
lafhterlearn/cmd_api/data.py
lafhterlearn/cmd_api/evaluate.py
lafhterlearn/cmd_api/extract_fonts.py
lafhterlearn/cmd_api/finetune.py
lafhterlearn/cmd_api/learn_ngrams.py
lafhterlearn/cmd_api/make_session.py
lafhterlearn/cmd_api/pretrain.py
lafhterlearn/cmd_api/transcribe.py
lafhterlearn/cmd_api/visualize_fonts.py
lafhterlearn/cmd_api/word_distr.py
lafhterlearn/data_importers/__init__.py
lafhterlearn/data_importers/base.py
lafhterlearn/data_importers/iam.py
lafhterlearn-0.7.1.dist-info/METADATA
lafhterlearn-0.7.1.dist-info/WHEEL
lafhterlearn-0.7.1.dist-info/entry_points.txt
lafhterlearn-0.7.1.dist-info/licenses/LICENSE
lafhterlearn-0.7.1.dist-info/RECORD
