Metadata-Version: 2.1
Name: lafhterlearn
Version: 0.7.1
Summary: Label-Free Handwritten Text Recognition Learner implemented in Pytorch
Project-URL: Homepage, https://github.com/X-rayLaser/label-free-handwritten-text-recognition-learner
Project-URL: Documentation, https://github.com/X-rayLaser/label-free-handwritten-text-recognition-learner/wiki
Author-email: Evgenii Dolotov <supernovaprotocol@gmail.com>
License-File: LICENSE
Keywords: deep learning,handwriting recognition,handwritten text recognition,lafhterlearn,machine learning,neural networks,ocr,pytorch
Classifier: Intended Audience :: Developers
Classifier: Intended Audience :: Science/Research
Classifier: License :: OSI Approved :: MIT License
Classifier: Operating System :: OS Independent
Classifier: Programming Language :: Python :: 3
Classifier: Topic :: Scientific/Engineering
Classifier: Topic :: Scientific/Engineering :: Artificial Intelligence
Classifier: Topic :: Scientific/Engineering :: Image Recognition
Classifier: Topic :: Scientific/Engineering :: Mathematics
Classifier: Topic :: Software Development
Classifier: Topic :: Software Development :: Libraries
Classifier: Topic :: Software Development :: Libraries :: Python Modules
Classifier: Topic :: Utilities
Requires-Python: >=3.8.9
Requires-Dist: h5py
Requires-Dist: nltk
Requires-Dist: numpy
Requires-Dist: pillow<10,>=8.4.0
Requires-Dist: pyyaml
Requires-Dist: torch<2
Requires-Dist: torchmetrics<1
Requires-Dist: torchvision<1
